odoo/addons/account_peppol_send_immediate/README.rst
odoo/addons/account_peppol_send_immediate/__init__.py
odoo/addons/account_peppol_send_immediate/__manifest__.py
odoo/addons/account_peppol_send_immediate/readme/CONTRIBUTORS.md
odoo/addons/account_peppol_send_immediate/readme/CREDITS.md
odoo/addons/account_peppol_send_immediate/readme/DESCRIPTION.md
odoo/addons/account_peppol_send_immediate/static/description/icon.png
odoo/addons/account_peppol_send_immediate/static/description/index.html
odoo/addons/account_peppol_send_immediate/wizard/__init__.py
odoo/addons/account_peppol_send_immediate/wizard/account_invoice_send.py
odoo_addon_account_peppol_send_immediate-16.0.1.0.0.2.dist-info/METADATA
odoo_addon_account_peppol_send_immediate-16.0.1.0.0.2.dist-info/WHEEL
odoo_addon_account_peppol_send_immediate-16.0.1.0.0.2.dist-info/top_level.txt
odoo_addon_account_peppol_send_immediate-16.0.1.0.0.2.dist-info/RECORD
